skill_ovos_news/LICENSE
skill_ovos_news/MANIFEST.in
skill_ovos_news/News.json
skill_ovos_news/README.md
skill_ovos_news/__init__.py
skill_ovos_news/version.py
skill_ovos_news/locale/ca-es/ca.voc
skill_ovos_news/locale/ca-es/de.voc
skill_ovos_news/locale/ca-es/en-au.voc
skill_ovos_news/locale/ca-es/en-ca.voc
skill_ovos_news/locale/ca-es/en-gb.voc
skill_ovos_news/locale/ca-es/en-us.voc
skill_ovos_news/locale/ca-es/en.voc
skill_ovos_news/locale/ca-es/es.voc
skill_ovos_news/locale/ca-es/euro.voc
skill_ovos_news/locale/ca-es/euronews.voc
skill_ovos_news/locale/ca-es/fi.voc
skill_ovos_news/locale/ca-es/fr.voc
skill_ovos_news/locale/ca-es/fr24.voc
skill_ovos_news/locale/ca-es/global_news.intent
skill_ovos_news/locale/ca-es/it.voc
skill_ovos_news/locale/ca-es/news.error
skill_ovos_news/locale/ca-es/news.intent
skill_ovos_news/locale/ca-es/news.voc
skill_ovos_news/locale/ca-es/nl.voc
skill_ovos_news/locale/ca-es/pt-pt.voc
skill_ovos_news/locale/ca-es/rt.voc
skill_ovos_news/locale/ca-es/ru.voc
skill_ovos_news/locale/ca-es/skill.json
skill_ovos_news/locale/ca-es/sv.voc
skill_ovos_news/locale/ca-es/video.voc
skill_ovos_news/locale/ca-es/world_news.voc
skill_ovos_news/locale/da-dk/ca.voc
skill_ovos_news/locale/da-dk/de.voc
skill_ovos_news/locale/da-dk/en-au.voc
skill_ovos_news/locale/da-dk/en-ca.voc
skill_ovos_news/locale/da-dk/en-gb.voc
skill_ovos_news/locale/da-dk/en-us.voc
skill_ovos_news/locale/da-dk/en.voc
skill_ovos_news/locale/da-dk/es.voc
skill_ovos_news/locale/da-dk/euro.voc
skill_ovos_news/locale/da-dk/euronews.voc
skill_ovos_news/locale/da-dk/fi.voc
skill_ovos_news/locale/da-dk/fr.voc
skill_ovos_news/locale/da-dk/fr24.voc
skill_ovos_news/locale/da-dk/global_news.intent
skill_ovos_news/locale/da-dk/it.voc
skill_ovos_news/locale/da-dk/news.error
skill_ovos_news/locale/da-dk/news.intent
skill_ovos_news/locale/da-dk/news.voc
skill_ovos_news/locale/da-dk/nl.voc
skill_ovos_news/locale/da-dk/pt-pt.voc
skill_ovos_news/locale/da-dk/rt.voc
skill_ovos_news/locale/da-dk/ru.voc
skill_ovos_news/skill_news.egg-info/PKG-INFO
skill_ovos_news/skill_news.egg-info/SOURCES.txt
skill_ovos_news/skill_news.egg-info/dependency_links.txt
skill_ovos_news/skill_news.egg-info/entry_points.txt
skill_ovos_news/skill_news.egg-info/requires.txt
skill_ovos_news/skill_news.egg-info/top_level.txt
skill_news-0.4.3.dist-info/LICENSE
skill_news-0.4.3.dist-info/METADATA
skill_news-0.4.3.dist-info/WHEEL
skill_news-0.4.3.dist-info/entry_points.txt
skill_news-0.4.3.dist-info/top_level.txt
skill_news-0.4.3.dist-info/RECORD
